pangukitsappdev/__init__.py
pangukitsappdev/agent/__init__.py
pangukitsappdev/agent/agent_action.py
pangukitsappdev/agent/agent_session.py
pangukitsappdev/agent/react_agent.py
pangukitsappdev/agent/react_pangu_agent.py
pangukitsappdev/api/__init__.py
pangukitsappdev/api/common_config.py
pangukitsappdev/api/config_loader.py
pangukitsappdev/api/crypto_util.py
pangukitsappdev/api/schema.py
pangukitsappdev/api/agent/__init__.py
pangukitsappdev/api/agent/base.py
pangukitsappdev/api/doc_split/__init__.py
pangukitsappdev/api/doc_split/base.py
pangukitsappdev/api/doc_split/factory.py
pangukitsappdev/api/doc_split/split_config.py
pangukitsappdev/api/embeddings/__init__.py
pangukitsappdev/api/embeddings/base.py
pangukitsappdev/api/embeddings/embedding_config.py
pangukitsappdev/api/embeddings/factory.py
pangukitsappdev/api/llms/__init__.py
pangukitsappdev/api/llms/base.py
pangukitsappdev/api/llms/factory.py
pangukitsappdev/api/llms/llm_config.py
pangukitsappdev/api/memory/__init__.py
pangukitsappdev/api/memory/message_history_config.py
pangukitsappdev/api/memory/cache/__init__.py
pangukitsappdev/api/memory/cache/base.py
pangukitsappdev/api/memory/cache/cache_config.py
pangukitsappdev/api/memory/cache/factory.py
pangukitsappdev/api/memory/vector/__init__.py
pangukitsappdev/api/memory/vector/base.py
pangukitsappdev/api/memory/vector/factory.py
pangukitsappdev/api/memory/vector/vector_config.py
pangukitsappdev/api/prompt/__init__.py
pangukitsappdev/api/prompt/prompt_config.py
pangukitsappdev/api/retriever/__init__.py
pangukitsappdev/api/retriever/base.py
pangukitsappdev/api/retriever/retriever_config.py
pangukitsappdev/api/skill/__init__.py
pangukitsappdev/api/skill/base.py
pangukitsappdev/api/skill/factory.py
pangukitsappdev/api/tool/__init__.py
pangukitsappdev/api/tool/base.py
pangukitsappdev/auth/__init__.py
pangukitsappdev/auth/iam.py
pangukitsappdev/cache/__init__.py
pangukitsappdev/cache/gptcache_adapter.py
pangukitsappdev/cache/in_memory.py
pangukitsappdev/cache/sql.py
pangu_kits_app_dev_py-2.4.0.dist-info/METADATA
pangu_kits_app_dev_py-2.4.0.dist-info/WHEEL
pangu_kits_app_dev_py-2.4.0.dist-info/top_level.txt
pangu_kits_app_dev_py-2.4.0.dist-info/RECORD
