Metadata-Version: 2.1
Name: pangu-kits-app-dev-py
Version: 2.4.0
Summary: App development kit for Pangu
Classifier: Topic :: Software Development :: Libraries :: Application Frameworks
Classifier: Development Status :: 3 - Alpha
Classifier: Intended Audience :: Developers
Classifier: Programming Language :: Python :: 3.9
Requires-Python: >=3.7
Requires-Dist: langchain ~=0.1.11
Requires-Dist: jinja2 ~=3.1.2
Requires-Dist: requests >=2.31.0
Requires-Dist: pydantic ~=1.10.9
Requires-Dist: python-dotenv ~=0.21.0
Requires-Dist: sseclient-py ~=1.7.2
Requires-Dist: elasticsearch ~=7.6.0
Requires-Dist: urllib3 ~=1.26.16
Requires-Dist: cachetools ~=5.3.1
Requires-Dist: langchain-openai ~=0.0.8
Provides-Extra: gptcache
Requires-Dist: gptcache ~=0.1.37 ; extra == 'gptcache'
Requires-Dist: redis ~=4.5.5 ; extra == 'gptcache'
Requires-Dist: redis-om ~=0.1.3 ; extra == 'gptcache'
Provides-Extra: redis
Requires-Dist: redis ~=4.5.5 ; extra == 'redis'
Provides-Extra: sqlcache
Requires-Dist: pymysql ~=1.1.0 ; extra == 'sqlcache'
Requires-Dist: SQLAlchemy ~=2.0.19 ; extra == 'sqlcache'
